{
	"parent": "minecraft:block/block",
	"ambientocclusion": false,
	"textures": {
		"1": "block/coal_block",
		"particle": "block/coal_block"
	},
	"elements": [
		{
			"from": [0, 0, 7],
			"to": [2, 2, 9],
			"rotation": {"angle": 0, "axis": "y", "origin": [8, 8, 16]},
			"faces": {
				"north": {"texture": "#1"},
				"east": {"texture": "#1"},
				"south": {"texture": "#1"},
				"west": {"texture": "#1"},
				"up": {"texture": "#1"},
				"down": {"texture": "#1"}
			}
		},
		{
			"from": [0, 0, 0],
			"to": [2, 2, 1],
			"rotation": {"angle": 0, "axis": "y", "origin": [8, 8, 9]},
			"faces": {
				"east": {"texture": "#1"},
				"south": {"texture": "#1"},
				"west": {"texture": "#1"},
				"up": {"texture": "#1"},
				"down": {"texture": "#1"}
			}
		},
		{
			"from": [0, 0, 15],
			"to": [2, 2, 16],
			"rotation": {"angle": 0, "axis": "y", "origin": [8, 8, 23]},
			"faces": {
				"north": {"texture": "#1"},
				"east": {"texture": "#1"},
				"west": {"texture": "#1"},
				"up": {"texture": "#1"},
				"down": {"texture": "#1"}
			}
		},
		{
			"from": [14, 0, 7],
			"to": [16, 2, 9],
			"rotation": {"angle": 0, "axis": "y", "origin": [22, 8, 16]},
			"faces": {
				"north": {"texture": "#1"},
				"east": {"texture": "#1"},
				"south": {"texture": "#1"},
				"west": {"texture": "#1"},
				"up": {"texture": "#1"},
				"down": {"texture": "#1"}
			}
		},
		{
			"from": [14, 0, 0],
			"to": [16, 2, 1],
			"rotation": {"angle": 0, "axis": "y", "origin": [22, 8, 9]},
			"faces": {
				"east": {"texture": "#1"},
				"south": {"texture": "#1"},
				"west": {"texture": "#1"},
				"up": {"texture": "#1"},
				"down": {"texture": "#1"}
			}
		},
		{
			"from": [14, 0, 15],
			"to": [16, 2, 16],
			"rotation": {"angle": 0, "axis": "y", "origin": [22, 8, 23]},
			"faces": {
				"north": {"texture": "#1"},
				"east": {"texture": "#1"},
				"west": {"texture": "#1"},
				"up": {"texture": "#1"},
				"down": {"texture": "#1"}
			}
		}
	]
}